{
    "id": "atmosphericPressureMeasurement",
    "version": 1,
    "status": "proposed",
    "name": "Atmospheric Pressure Measurement",
    "ephemeral": false,
    "attributes": {
        "atmosphericPressure": {
            "schema": {
                "type": "object",
                "properties": {
                    "value": {
                        "type": "number",
                        "minimum": 0
                    },
                    "unit": {
                        "type": "string",
                        "enum": [
                            "kPa",
                            "hPa",
                            "bar",
                            "mbar",
                            "mmHg",
                            "inHg",
                            "atm",
                            "psi"
                        ],
                        "default": "kPa"
                    }
                },
                "additionalProperties": false,
                "required": [
                    "value"
                ]
            },
            "enumCommands": []
        }
    },
    "commands": []
}