{
    "detailView": [
        {
            "label": "___PO_CODE_SMARTTHINGS_DREAM_SAC_HEADER_PM_1_0_M_AIR_QUALITY",
            "displayType": "state",
            "state": {
                "label": "{{veryFineDustLevel.value}}"
            }
        }
    ],
    "automation": {
        "conditions": [
            {
                "label": "___PO_CODE_SMARTTHINGS_DREAM_SAC_HEADER_PM_1_0_M_AIR_QUALITY",
                "displayType": "numberField",
                "numberField": {
                    "value": "veryFineDustLevel.value",
                    "valueType": "integer"
                }
            }
        ],
        "actions": []
    },
    "id": "veryFineDustSensor",
    "version": 1
}